eloqua/__init__.py
eloqua/eloqua.py
eloqua/errors.py
eloqua/paths.py
test/__init__.py
test/creds.py
test/example_creds.py
test/test.py
test/test_data.py
eloqua_lib-0.0.1.dist-info/LICENSE
eloqua_lib-0.0.1.dist-info/METADATA
eloqua_lib-0.0.1.dist-info/WHEEL
eloqua_lib-0.0.1.dist-info/top_level.txt
eloqua_lib-0.0.1.dist-info/RECORD
