Metadata-Version: 2.1
Name: eloqua-lib
Version: 0.0.1
Summary: Eloqua library
Home-page: https://github.com/jnorton2/Eloqua
Author: Josh Norton
Author-email: joshrnorton75@gmail.com
License: UNKNOWN
Platform: UNKNOWN
Classifier: Programming Language :: Python :: 3
Classifier: License :: OSI Approved :: MIT License
Classifier: Operating System :: OS Independent
